{
  "normal": {
    "mean_duration": 324.822,
    "std_duration": 0.0,
    "mean_confidence": 76.27070365620317,
    "std_confidence": 0.0,
    "mean_final_success": 0.47,
    "std_final_success": 0.0,
    "max_duration": 500,
    "num_runs": 1,
    "first_success_episode": 479.0
  },
  "depressed_mild": {
    "mean_duration": 137.471,
    "std_duration": 0.0,
    "mean_confidence": 58.80762006605735,
    "std_confidence": 0.0,
    "mean_final_success": 0.054,
    "std_final_success": 0.0,
    "max_duration": 500,
    "num_runs": 1,
    "first_success_episode": 307.0
  }
}